ListFunctionMappers/ListFunctionMappers.py
ListFunctionMappers/__init__.py
ListFunctionMappers-0.0.2.dist-info/METADATA
ListFunctionMappers-0.0.2.dist-info/WHEEL
ListFunctionMappers-0.0.2.dist-info/top_level.txt
ListFunctionMappers-0.0.2.dist-info/RECORD
