Metadata-Version: 2.1
Name: ListFunctionMappers
Version: 0.0.2
Summary: package for map a list
Home-page: https://github.com/pypa/sampleproject
Author: Tantely
Author-email: tantelitiana22@gmail.com
License: UNKNOWN
Platform: UNKNOWN
Classifier: Programming Language :: Python :: 3
Classifier: License :: OSI Approved
Classifier: Operating System :: OS Independent
Requires-Python: >=3.6
